{"Basement Landing":{"B":"x","G":"x","U":null,"R":null,"E":null,"O":null,"I":null,"D":null},"Entrance Hall":{"B":null,"G":"x","U":null,"R":null,"E":null,"O":null,"I":null,"D":null},"Foyer":{"B":null,"G":"x","U":null,"R":null,"E":null,"O":null,"I":null,"D":null},"Grand Staircase":{"B":null,"G":"x","U":null,"R":null,"E":null,"O":null,"I":null,"D":null},"Upper Landing":{"B":null,"G":null,"U":"x","R":null,"E":null,"O":null,"I":null,"D":null},"Roof Landing":{"B":null,"G":null,"U":null,"R":"x","E":null,"O":null,"I":null,"D":null},"Catacombs":{"B":"x","G":null,"U":null,"R":null,"E":null,"O":"x","I":null,"D":null},"Cave":{"B":"x","G":null,"U":null,"R":null,"E":"x","O":null,"I":null,"D":null},"Chasm":{"B":"x","G":null,"U":null,"R":null,"E":null,"O":null,"I":null,"D":null},"Crypt":{"B":"x","G":null,"U":null,"R":null,"E":"x","O":null,"I":null,"D":null},"Dungeon":{"B":"x","G":null,"U":null,"R":null,"E":null,"O":"x","I":null,"D":null},"Furnace Room":{"B":"x","G":null,"U":null,"R":null,"E":null,"O":"x","I":null,"D":null},"Larder":{"B":"x","G":null,"U":null,"R":null,"E":null,"O":null,"I":"x","D":null},"Pentagram Chamber":{"B":"x","G":null,"U":null,"R":null,"E":null,"O":"x","I":null,"D":null},"Stairs from Basement":{"B":"x","G":null,"U":null,"R":null,"E":null,"O":null,"I":null,"D":null},"Storm Cellar":{"B":"x","G":null,"U":null,"R":null,"E":null,"O":null,"I":"x","D":"x"},"Underground Lake":{"B":"x","G":null,"U":null,"R":null,"E":"x","O":null,"I":null,"D":null},"Wine Cellar":{"B":"x","G":null,"U":null,"R":null,"E":null,"O":null,"I":"x","D":null},"Panic Room":{"B":"x","G":"x","U":"x","R":"x","E":"x","O":null,"I":null,"D":null},"Creaky Hallway":{"B":"x","G":"x","U":"x","R":null,"E":null,"O":null,"I":null,"D":null},"Dusty Hallway":{"B":"x","G":"x","U":"x","R":null,"E":null,"O":null,"I":null,"D":null},"Game Room":{"B":"x","G":"x","U":"x","R":null,"E":"x","O":null,"I":null,"D":null},"Junk Room":{"B":"x","G":"x","U":"x","R":null,"E":null,"O":"x","I":null,"D":null},"Mystic Elevator":{"B":"x","G":"x","U":"x","R":null,"E":null,"O":null,"I":null,"D":null},"Organ Room":{"B":"x","G":"x","U":"x","R":null,"E":"x","O":null,"I":null,"D":null},"Statuary Corridor":{"B":"x","G":"x","U":"x","R":null,"E":"x","O":null,"I":null,"D":null},"Abandoned Room":{"B":"x","G":"x","U":null,"R":null,"E":null,"O":"x","I":null,"D":null},"Arsenal":{"B":"x","G":"x","U":null,"R":null,"E":null,"O":null,"I":"x","D":"x"},"Kitchen":{"B":"x","G":"x","U":null,"R":null,"E":null,"O":"x","I":null,"D":null},"Laundry":{"B":"x","G":"x","U":null,"R":null,"E":null,"O":null,"I":"x","D":"x"},"Menagerie":{"B":"x","G":"x","U":null,"R":null,"E":"x","O":null,"I":null,"D":"x"},"Locked Room":{"B":"x","G":null,"U":"x","R":"x","E":"x","O":null,"I":null,"D":null},"Gymnasium":{"B":"x","G":null,"U":"x","R":null,"E":null,"O":"x","I":null,"D":null},"Operating Laboratory":{"B":"x","G":null,"U":"x","R":null,"E":"x","O":null,"I":null,"D":null},"Research Laboratory":{"B":"x","G":null,"U":"x","R":null,"E":"x","O":null,"I":null,"D":null},"Servants' Quarters":{"B":"x","G":null,"U":"x","R":null,"E":null,"O":"x","I":null,"D":null},"Storeroom":{"B":"x","G":null,"U":"x","R":null,"E":null,"O":null,"I":"x","D":null},"Vault":{"B":"x","G":null,"U":"x","R":null,"E":null,"O":null,"I":"x","D":null},"Ballroom":{"B":null,"G":"x","U":null,"R":null,"E":"x","O":null,"I":null,"D":null},"Coal Chute":{"B":null,"G":"x","U":null,"R":null,"E":null,"O":null,"I":null,"D":null},"Dining Room":{"B":null,"G":"x","U":null,"R":null,"E":null,"O":"x","I":null,"D":null},"Gardens":{"B":null,"G":"x","U":null,"R":null,"E":"x","O":null,"I":null,"D":null},"Graveyard":{"B":null,"G":"x","U":null,"R":null,"E":"x","O":null,"I":null,"D":null},"Patio":{"B":null,"G":"x","U":null,"R":null,"E":"x","O":null,"I":null,"D":null},"Tree House":{"B":null,"G":"x","U":null,"R":null,"E":"x","O":null,"I":null,"D":null},"Spiral Staircase":{"B":null,"G":"x","U":"x","R":"x","E":null,"O":null,"I":null,"D":null},"Study":{"B":null,"G":"x","U":"x","R":"x","E":null,"O":"x","I":null,"D":"x"},"Bathroom":{"B":null,"G":"x","U":"x","R":null,"E":"x","O":null,"I":null,"D":null},"Bloody Room":{"B":null,"G":"x","U":"x","R":null,"E":null,"O":null,"I":"x","D":null},"Chapel":{"B":null,"G":"x","U":"x","R":null,"E":"x","O":null,"I":null,"D":null},"Charred Room":{"B":null,"G":"x","U":"x","R":null,"E":null,"O":"x","I":null,"D":null},"Collapsed Room":{"B":null,"G":"x","U":"x","R":null,"E":null,"O":null,"I":null,"D":null},"Conservatory":{"B":null,"G":"x","U":"x","R":null,"E":"x","O":null,"I":null,"D":null},"Library":{"B":null,"G":"x","U":"x","R":null,"E":"x","O":null,"I":null,"D":null},"Theater":{"B":null,"G":"x","U":"x","R":null,"E":null,"O":"x","I":null,"D":null},"Drawing Room":{"B":null,"G":null,"U":"x","R":"x","E":"x","O":"x","I":"x","D":"x"},"Nursery":{"B":null,"G":null,"U":"x","R":"x","E":null,"O":"x","I":null,"D":null},"Sewing Room":{"B":null,"G":null,"U":"x","R":"x","E":null,"O":null,"I":"x","D":"x"},"Solarium":{"B":null,"G":null,"U":"x","R":"x","E":null,"O":null,"I":"x","D":null},"Widow's Walk":{"B":null,"G":null,"U":"x","R":"x","E":"x","O":null,"I":null,"D":null},"Attic":{"B":null,"G":null,"U":"x","R":null,"E":"x","O":null,"I":null,"D":null},"Balcony":{"B":null,"G":null,"U":"x","R":null,"E":"x","O":null,"I":null,"D":null},"Bedroom":{"B":null,"G":null,"U":"x","R":null,"E":"x","O":null,"I":null,"D":null},"Gallery":{"B":null,"G":null,"U":"x","R":null,"E":"x","O":null,"I":null,"D":null},"Master Bedroom":{"B":null,"G":null,"U":"x","R":null,"E":null,"O":"x","I":null,"D":null},"Tower":{"B":null,"G":null,"U":"x","R":null,"E":"x","O":null,"I":null,"D":null},"Rookery":{"B":null,"G":null,"U":null,"R":"x","E":null,"O":"x","I":null,"D":null}}